onfrontiers/__init__.py
onfrontiers/client.py
onfrontiers/py.typed
onfrontiers-0.0.5.dist-info/METADATA
onfrontiers-0.0.5.dist-info/WHEEL
onfrontiers-0.0.5.dist-info/licenses/LICENSE
onfrontiers-0.0.5.dist-info/RECORD
